argparseware/__init__.py
argparseware/common.py
argparseware/config.py
argparseware/core.py
argparseware/server.py
argparseware/setuputils.py
argparseware/utils.py
argparseware/commands/__init__.py
argparseware/commands/flask_cli.py
argparseware/commands/setuptools.py
argparseware-0.9.9.dist-info/LICENSE
argparseware-0.9.9.dist-info/METADATA
argparseware-0.9.9.dist-info/WHEEL
argparseware-0.9.9.dist-info/top_level.txt
argparseware-0.9.9.dist-info/RECORD
