Metadata-Version: 2.1
Name: argparseware
Version: 0.9.9
Summary: argparseware middleware library
Home-page: https://github.com/relevance-io/argparseware
Author: Francis Lacroix
Author-email: f@relevance.io
Maintainer: Francis Lacroix
Maintainer-email: f@relevance.io
License: MIT
Platform: UNKNOWN
Provides-Extra: all
Requires-Dist: anyconfig (<0.10,>=0.9.1) ; extra == 'all'
Requires-Dist: PyYAML (<4,>=3.12) ; extra == 'all'
Requires-Dist: Flask (<2,>=1.1.1) ; extra == 'all'
Requires-Dist: gunicorn (<21,>=20.0.4) ; extra == 'all'
Requires-Dist: gevent (<21,>=20.6.2) ; extra == 'all'
Provides-Extra: config
Requires-Dist: anyconfig (<0.10,>=0.9.1) ; extra == 'config'
Requires-Dist: PyYAML (<4,>=3.12) ; extra == 'config'
Provides-Extra: wsgi
Requires-Dist: Flask (<2,>=1.1.1) ; extra == 'wsgi'
Requires-Dist: gunicorn (<21,>=20.0.4) ; extra == 'wsgi'
Requires-Dist: gevent (<21,>=20.6.2) ; extra == 'wsgi'
